uk_postcodes_parsing/__init__.py
uk_postcodes_parsing/database_manager.py
uk_postcodes_parsing/fix.py
uk_postcodes_parsing/postcode_database.py
uk_postcodes_parsing/postcode_utils.py
uk_postcodes_parsing/postcodes_nov_2024.py
uk_postcodes_parsing/ukpostcode.py
uk_postcodes_parsing-2.0.4.dist-info/METADATA
uk_postcodes_parsing-2.0.4.dist-info/WHEEL
uk_postcodes_parsing-2.0.4.dist-info/licenses/LICENSE
uk_postcodes_parsing-2.0.4.dist-info/RECORD
