Metadata-Version: 2.4
Name: uk_postcodes_parsing
Version: 2.0.4
Summary: A Python package to parse UK postcodes from text. Useful in applications such as OCR and IDP.
Project-URL: Homepage, https://github.com/anirudhgangwal/ukpostcodes
Project-URL: Bug Tracker, https://github.com/anirudhgangwal/ukpostcodes/issues
Author-email: Anirudh Gangwal <anirudh.gangwal.2015@gmail.com>
License-File: LICENSE
Classifier: License :: OSI Approved :: MIT License
Classifier: Operating System :: OS Independent
Classifier: Programming Language :: Python :: 3
Requires-Python: >=3.10
Provides-Extra: lint
Requires-Dist: black; extra == 'lint'
Provides-Extra: test
Requires-Dist: bandit[toml]; extra == 'test'
Requires-Dist: pytest; extra == 'test'
Requires-Dist: pytest-cov; extra == 'test'
